ipfy_asset_management_data_engineering_pipeline/Boursorama/__init__.py
ipfy_asset_management_data_engineering_pipeline/Boursorama/_data_integration_pipeline.py
ipfy_asset_management_data_engineering_pipeline/Boursorama/data_pipeline_execution.py
ipfy_asset_management_data_engineering_pipeline/CreditAgricoleAlsace/__init__.py
ipfy_asset_management_data_engineering_pipeline/CreditAgricoleAlsace/_data_integration_pipeline.py
ipfy_asset_management_data_engineering_pipeline/CreditAgricoleAlsace/_date_creation_process.py
ipfy_asset_management_data_engineering_pipeline/CreditAgricoleAlsace/data_pipeline_execution.py
ipfy_asset_management_data_engineering_pipeline/__init__.py
ipfy_asset_management_data_engineering_pipeline/_bank_data_type_detection.py
ipfy_asset_management_data_engineering_pipeline/constants/euro-swiss-franc-exchange-rate-historical.csv
ipfy_asset_management_data_engineering_pipeline/creditagricolenextbank/__init__.py
ipfy_asset_management_data_engineering_pipeline/creditagricolenextbank/_data_integration_pipeline.py
ipfy_asset_management_data_engineering_pipeline/creditagricolenextbank/data_pipeline_execution.py
ipfy_asset_management_data_engineering_pipeline/orchestration_and_process_execution.py
ipfy_asset_management_data_engineering_pipeline-0.2.0.dist-info/WHEEL
ipfy_asset_management_data_engineering_pipeline-0.2.0.dist-info/METADATA
ipfy_asset_management_data_engineering_pipeline-0.2.0.dist-info/RECORD
